codethemes/__init__.py
codethemes/main.py
codethemes-0.1.5.dist-info/LICENCE
codethemes-0.1.5.dist-info/METADATA
codethemes-0.1.5.dist-info/WHEEL
codethemes-0.1.5.dist-info/entry_points.txt
codethemes-0.1.5.dist-info/top_level.txt
codethemes-0.1.5.dist-info/zip-safe
codethemes-0.1.5.dist-info/RECORD
