Metadata-Version: 2.1
Name: codethemes
Version: 0.1.5
Summary: Import visual studio themes as linux terminal theme profiles
Home-page: https://github.com/saberd/codethemes
Author: saberd
Author-email: mail@saberd.com
License: BSD 3-Clause License
Keywords: vscode,theme,terminal,gnome,config
Classifier: Topic :: Desktop Environment :: Gnome
Classifier: Programming Language :: Python :: 3
Classifier: License :: OSI Approved :: MIT License
Classifier: Topic :: Utilities
License-File: LICENCE
Requires-Dist: json5
Requires-Dist: dconfjson
